LICENSE
MANIFEST.in
README.md
setup.py
deerdawn/__init__.py
deerdawn/client.py
deerdawn/types.py
deerdawn.egg-info/PKG-INFO
deerdawn.egg-info/SOURCES.txt
deerdawn.egg-info/dependency_links.txt
deerdawn.egg-info/requires.txt
deerdawn.egg-info/top_level.txt