Metadata-Version: 2.1
Name: deerdawn
Version: 1.0.0
Summary: Official Python SDK for DeerDawn - AI governance and decision control platform
Home-page: https://github.com/deerdawn/deerdawn-sdk-python
Author: DeerDawn
Author-email: support@deerdawn.com
Project-URL: Bug Tracker, https://github.com/deerdawn/deerdawn-sdk-python/issues
Project-URL: Documentation, https://deerdawn.com/docs/sdks
Project-URL: Homepage, https://deerdawn.com
Keywords: deerdawn ai-governance decision-control policy-engine ai-security
Classifier: Development Status :: 5 - Production/Stable
Classifier: Intended Audience :: Developers
Classifier: License :: OSI Approved :: MIT License
Classifier: Operating System :: OS Independent
Classifier: Programming Language :: Python :: 3
Classifier: Programming Language :: Python :: 3.7
Classifier: Programming Language :: Python :: 3.8
Classifier: Programming Language :: Python :: 3.9
Classifier: Programming Language :: Python :: 3.10
Classifier: Programming Language :: Python :: 3.11
Classifier: Programming Language :: Python :: 3.12
Classifier: Topic :: Software Development :: Libraries :: Python Modules
Requires-Python: >=3.7
Provides-Extra: dev
License-File: LICENSE
